sdk/bookmark.py
sdk/bookmark_response.py
sdk/bookmark_tag.py
sdk/client.py
sdk/fields.py
sdk/hide_reply.py
sdk/hide_reply_response.py
sdk/like.py
sdk/like_response.py
sdk/pagination.py
sdk/quote_tag.py
sdk/retweet_tag.py
sdk/search_tag.py
sdk/single_tweet.py
sdk/trend.py
sdk/trend_collection.py
sdk/trends_tag.py
sdk/tweet.py
sdk/tweet_collection.py
sdk/tweet_create.py
sdk/tweet_create_response.py
sdk/tweet_delete.py
sdk/tweet_delete_response.py
sdk/tweet_details.py
sdk/tweet_entity.py
sdk/tweet_geo.py
sdk/tweet_media.py
sdk/tweet_poll.py
sdk/tweet_reply.py
sdk/tweet_tag.py
sdk/tweet_usage.py
sdk/tweet_usage_response.py
sdk/usage_tag.py
sdk/user.py
sdk/user_collection.py
sdk/user_tag.py
sdkfabric_twitter-3.0.9.dist-info/LICENSE
sdkfabric_twitter-3.0.9.dist-info/METADATA
sdkfabric_twitter-3.0.9.dist-info/WHEEL
sdkfabric_twitter-3.0.9.dist-info/top_level.txt
sdkfabric_twitter-3.0.9.dist-info/RECORD
